acheron/__init__.py
acheron/__main__.py
acheron/build_info.py
acheron/device_logging.py
acheron/logging.py
acheron/version.py
acheron/calc_process/__init__.py
acheron/calc_process/remote.py
acheron/calc_process/runnner.py
acheron/calc_process/types.py
acheron/connectivity/__init__.py
acheron/connectivity/alert_emailer.py
acheron/connectivity/connectivity_manager.py
acheron/connectivity/event_upload.py
acheron/connectivity/modbus.py
acheron/connectivity/s3upload.py
acheron/connectivity/socket_handler.py
acheron/core/__init__.py
acheron/core/__main__.py
acheron/core/calibration.py
acheron/core/device_controller.py
acheron/core/dispatcher.py
acheron/core/main_schedule.py
acheron/core/preferences.py
acheron/core/radio_scan.py
acheron/core/single_app_instance.py
acheron/core/update_func_limiter.py
acheron/device_process/__init__.py
acheron/device_process/bootloader.py
acheron/device_process/compressor.py
acheron/device_process/hardware_test_funcs.py
acheron/device_process/proxy.py
acheron/device_process/proxy_remote.py
acheron/device_process/remote_funcs.py
acheron/device_process/rgb_manager.py
acheron/device_process/schedule.py
acheron/device_process/stream_controller.py
acheron/device_process/writer.py
acheron/disk/__init__.py
acheron/disk/disk_schedule.py
acheron/disk/disk_trigger.py
acheron/disk/schedule_reader.py
acheron/gui/__init__.py
acheron/gui/__main__.py
acheron/gui/about.py
acheron/gui/acheron_rc.py
acheron/gui/calibration.py
acheron/gui/change_stream_dialog.py
acheron/gui/connectivity_dialog.py
acheron/gui/ctrl_var_panel.py
acheron/gui/ctrl_var_widget.py
acheron/gui/device_tab.py
acheron/gui/download_firmware_dialog.py
acheron/gui/edit_alert_dialog.py
acheron/gui/gui_log.py
acheron/gui/hardware_tests.py
acheron/gui/led_control_widget.py
acheron/gui/plotmain.py
acheron/gui/preferences_dialog.py
acheron/gui/radio_detail_scan.py
acheron/gui/radio_panel.py
acheron/gui/remote_panel.py
acheron/gui/rf_power_panel.py
acheron/gui/rf_test_dialog.py
acheron-3.0.0.dist-info/LICENSE.txt
acheron-3.0.0.dist-info/METADATA
acheron-3.0.0.dist-info/WHEEL
acheron-3.0.0.dist-info/entry_points.txt
acheron-3.0.0.dist-info/top_level.txt
acheron-3.0.0.dist-info/RECORD
