Metadata-Version: 2.1
Name: acheron
Version: 3.0.0
Summary: Plotting and recording program for Asphodel devices
Home-page: https://bitbucket.org/suprocktech/acheron
Author: Suprock Technologies, LLC
Author-email: inquiries@suprocktech.com
License: UNKNOWN
Keywords: asphodel suprock apd
Platform: UNKNOWN
Classifier: Programming Language :: Python :: 3
Classifier: License :: OSI Approved :: ISC License (ISCL)
Classifier: Operating System :: OS Independent
Classifier: Topic :: System :: Hardware
Requires-Python: >=3.10
License-File: LICENSE.txt
Requires-Dist: asphodel
Requires-Dist: boto3
Requires-Dist: croniter
Requires-Dist: diskcache
Requires-Dist: hyperborea
Requires-Dist: intervaltree
Requires-Dist: numpy
Requires-Dist: packaging
Requires-Dist: psutil
Requires-Dist: pydantic
Requires-Dist: pymodbus (<3,>=2.5.3)
Requires-Dist: pyqtgraph
Requires-Dist: pyserial
Requires-Dist: PySide6-Essentials
Requires-Dist: requests
Requires-Dist: setproctitle
